CHANGES.rst
HACKING.rst
LICENSE
MANIFEST.in
README.rst
VERSION
setup.cfg
setup.py
doc/Makefile
doc/index.txt
doc/vulnix-whitelist.5.md
doc/vulnix.1.md
src/vulnix/__init__.py
src/vulnix/derivation.py
src/vulnix/main.py
src/vulnix/nix.py
src/vulnix/nvd.py
src/vulnix/output.py
src/vulnix/resource.py
src/vulnix/utils.py
src/vulnix/vulnerability.py
src/vulnix/whitelist.py
src/vulnix.egg-info/PKG-INFO
src/vulnix.egg-info/SOURCES.txt
src/vulnix.egg-info/dependency_links.txt
src/vulnix.egg-info/entry_points.txt
src/vulnix.egg-info/not-zip-safe
src/vulnix.egg-info/requires.txt
src/vulnix.egg-info/top_level.txt
src/vulnix/tests/conftest.py
src/vulnix/tests/nvd_test.py
src/vulnix/tests/output_test.py
src/vulnix/tests/resource_test.py
src/vulnix/tests/store_test.py
src/vulnix/tests/test_derivation.py
src/vulnix/tests/utils_test.py
src/vulnix/tests/vulnerability_test.py
src/vulnix/tests/whitelist_test.py
src/vulnix/tests/fixtures/CVE-2010-0748.json
src/vulnix/tests/fixtures/CVE-2015-1789.json
src/vulnix/tests/fixtures/CVE-2016-2183.json
src/vulnix/tests/fixtures/CVE-2019-10160.json
src/vulnix/tests/fixtures/CVE-2019-11041.json
src/vulnix/tests/fixtures/CVE-2019-6471.json
src/vulnix/tests/fixtures/audiofile-0.3.6.drv
src/vulnix/tests/fixtures/bzip2-1.0.6.0.1.drv
src/vulnix/tests/fixtures/cpio-2.12.drv
src/vulnix/tests/fixtures/cyrus-sasl-2.5.10.drv
src/vulnix/tests/fixtures/nvdcve-1.1-modified.json.gz
src/vulnix/tests/fixtures/pkgs.json
src/vulnix/tests/fixtures/structured-attrs-1.drv
src/vulnix/tests/fixtures/transmission-1.91.drv
src/vulnix/tests/fixtures/unzip-6.0.drv
src/vulnix/tests/fixtures/whitelist.toml
src/vulnix/tests/fixtures/whitelist.yaml