Metadata-Version: 2.1
Name: vulnix
Version: 1.10.1
Summary: Scans a Nix store for derivations that are affected by vulnerabilities.
Home-page: https://github.com/flyingcircusio/vulnix
Author: Flying Circus Internet Operations GmbH
Author-email: mail@flyingcircus.io
License: BSD-3-Clause
Keywords: security,nixos,nixpkgs,cve,nvd
Platform: UNKNOWN
Classifier: Development Status :: 5 - Production/Stable
Classifier: Environment :: Console
Classifier: Intended Audience :: System Administrators
Classifier: License :: OSI Approved :: BSD License
Classifier: Operating System :: POSIX
Classifier: Programming Language :: Python
Classifier: Programming Language :: Python :: 3 :: Only
Classifier: Programming Language :: Python :: 3.5
Classifier: Programming Language :: Python :: 3.6
Classifier: Programming Language :: Python :: 3.7
Classifier: Programming Language :: Python :: 3.8
Classifier: Topic :: System :: Systems Administration
Provides-Extra: test
